README.rst
setup.py
schemaconvertor/__init__.py
schemaconvertor/convertor.py
schemaconvertor.egg-info/PKG-INFO
schemaconvertor.egg-info/SOURCES.txt
schemaconvertor.egg-info/dependency_links.txt
schemaconvertor.egg-info/top_level.txt
schemaconvertor/tests/__init__.py
schemaconvertor/tests/test_convertor_0_1.py
schemaconvertor/tests/test_convertor_0_2.py
schemaconvertor/tests/test_demo.py