Metadata-Version: 1.1
Name: schemaconvertor
Version: 0.3.1.0
Summary: a tool to serialize objects by schema
Home-page: UNKNOWN
Author: Liu Yicong
Author-email: imyikong@gmail.com
License: BSD
Platform: UNKNOWN
Classifier: Development Status :: 3 - Alpha
Classifier: License :: OSI Approved :: BSD License
Classifier: Natural Language :: English
Classifier: Programming Language :: Python :: 2
Classifier: Programming Language :: Python :: 2.6
Classifier: Programming Language :: Python :: 2.7
